[{ "id": 8, "title": "电视", "child": [{ "id": 81, "img": "../iamges/banner-img/banner-tv1.png", "desig": "阿斐亚Aphaea" }, { "id": 82, "img": "../iamges/banner-img/banner-tv2.png", "desig": "全面屏电视" }, { "id": 83, "img": "../iamges/banner-img/banner-tv3.png", "desig": "超薄电视" }, { "id": 84, "img": "../iamges/banner-img/banner-tv4.png", "desig": "智能电视" }, { "id": 85, "img": "../iamges/banner-img/banner-tv5.png", "desig": "商用电视" }] }, { "id": 9, "title": "冰箱", "child": [{ "id": 91, "img": "../iamges/banner-img/banner-fridge1.png", "desig": "单门冰箱" }, { "id": 92, "img": "../iamges/banner-img/banner-fridge2.png", "desig": "双门冰箱" }, { "id": 93, "img": "../iamges/banner-img/banner-fridge3.png", "desig": "三门冰箱" }, { "id": 94, "img": "../iamges/banner-img/banner-fridge4.png", "desig": "多门冰箱" }, { "id": 95, "img": "../iamges/banner-img/banner-fridge5.png", "desig": "冷柜" }, { "id": 96, "img": "../iamges/banner-img/banner-fridge6.png", "desig": "直冷冰箱" }, { "id": 97, "img": "../iamges/banner-img/banner-fridge7.png", "desig": "风冷冰箱" }, { "id": 98, "img": "../iamges/banner-img/banner-fridge8.png", "desig": "混冷冰箱" }] }, { "id": 10, "title": "洗衣机", "child": [{ "id": 101, "img": "../iamges/banner-img/banner-wash1.png", "desig": "洗烘一体机" }, { "id": 102, "img": "../iamges/banner-img/banner-wash2.png", "desig": "滚筒洗衣机" }, { "id": 103, "img": "../iamges/banner-img/banner-wash3.png", "desig": "波轮洗衣机" }, { "id": 104, "img": "../iamges/banner-img/banner-wash4.png", "desig": "迷你洗衣机" }] }, { "id": 11, "title": "生活电器", "child": [{ "id": 111, "img": "../iamges/banner-img/banner-liver1.png", "desig": "电水壶" }, { "id": 112, "img": "../iamges/banner-img/banner-liver2.png", "desig": "养生壶" }, { "id": 113, "img": "../iamges/banner-img/banner-liver3.png", "desig": "破壁机" }, { "id": 114, "img": "../iamges/banner-img/banner-liver4.png", "desig": "料理机" }, { "id": 115, "img": "../iamges/banner-img/banner-liver5.png", "desig": "咖啡机" }, { "id": 116, "img": "../iamges/banner-img/banner-liver6.png", "desig": "多功能锅" }, { "id": 117, "img": "../iamges/banner-img/banner-liver7.png", "desig": "扫地机" }] }, { "id": 12, "title": "厨卫电器", "child": [{ "id": 121, "img": "../iamges/banner-img/banner-kitchen1.png", "desig": "电饭煲" }, { "id": 122, "img": "../iamges/banner-img/banner-kitchen2.png", "desig": "高压锅" }, { "id": 123, "img": "../iamges/banner-img/banner-kitchen3.png", "desig": "电磁炉" }, { "id": 124, "img": "../iamges/banner-img/banner-kitchen4.png", "desig": "电烤箱" }, { "id": 125, "img": "../iamges/banner-img/banner-kitchen5.png", "desig": "电陶炉" }, { "id": 126, "img": "../iamges/banner-img/banner-kitchen6.png", "desig": "空气炸锅" }, { "id": 127, "img": "../iamges/banner-img/banner-kitchen7.png", "desig": "油烟机" }, { "id": 128, "img": "../iamges/banner-img/banner-kitchen8.png", "desig": "燃气灶" }, { "id": 129, "img": "../iamges/banner-img/banner-kitchen9.png", "desig": "净水器" }, { "id": 1210, "img": "../iamges/banner-img/banner-kitchen10.png", "desig": "消毒柜" }, { "id": 1211, "img": "../iamges/banner-img/banner-kitchen11.png", "desig": "热水器" }] }, { "id": 13, "title": "智能硬件", "child": [{ "id": 131, "img": "../iamges/banner-img/banner-hardware1.png", "desig": "固态硬盘" }, { "id": 132, "img": "../iamges/banner-img/banner-hardware2.png", "desig": "麦克风" }, { "id": 133, "img": "../iamges/banner-img/banner-hardware3.png", "desig": "智能设摄像头" }, { "id": 134, "img": "../iamges/banner-img/banner-hardware4.png", "desig": "智能微投" }] }, { "id": 14, "title": "智能家居", "child": [{ "id": 141, "img": "../iamges/banner-img/banner-home1.png", "desig": "取暖器" }, { "id": 142, "img": "../iamges/banner-img/banner-home2.png", "desig": "照明" }, { "id": 143, "img": "../iamges/banner-img/banner-home3.png", "desig": "换气扇" }, { "id": 144, "img": "../iamges/banner-img/banner-home4.png", "desig": "智能电动窗帘" }, { "id": 145, "img": "../iamges/banner-img/banner-home5.png", "desig": "集成吊顶扣板" }, { "id": 146, "img": "../iamges/banner-img/banner-home6.png", "desig": "纳米微晶石" }] }, { "id": 15, "title": "K迷优品", "child": [{ "id": 151, "img": "../iamges/banner-img/banner-kmi1.png", "desig": "生活萌物" }, { "id": 152, "img": "../iamges/banner-img/banner-kmi2.png", "desig": "办公好物" }] }, { "id": 16, "title": "周边配件", "child": [{ "id": 161, "img": "../iamges/banner-img/banner-around1.png", "desig": "遥控器" }, { "id": 162, "img": "../iamges/banner-img/banner-around2.png", "desig": "挂架" }, { "id": 163, "img": "../iamges/banner-img/banner-around3.png", "desig": "延保" }, { "id": 164, "img": "../iamges/banner-img/banner-around4.png", "desig": "咪咕会员" }] }]